{"title":"Mea Khom Chhnas Pas Mea Phum Chhnerm id e5312ebec || part [ 54 ]","type":"vdolist","object_id":null,"pid":"e5312ebec","image":{"url":"https:\/\/blogger.googleusercontent.com\/img\/b\/R29vZ2xl\/AVvXsEj12lpuRukDHEAMBTVCN1YcrNDquCJUzevLXlulP4XZ_SU95ol4l1eUjGXdC7Ylr25ftW4i8YOcLfzxFcN3ZkCt_IMKI8A_A-mvEDbFUHx0PS7YwGjzThTLEIIGTsRcgDXEYtlKotKZbJc_jtAW3pEAYMOMVNvnOCJILzL7gXZmdGCZKIYl4v9oWrKZ\/w0\/%E1%9E%98%E1%9F%81%E1%9E%83%E1%9E%BB%E1%9F%86%E1%9E%86%E1%9F%92%E1%9E%93%E1%9E%B6%E1%9E%9F%E1%9E%94%E1%9F%89%E1%9F%87%E1%9E%98%E1%9F%81%E1%9E%97%E1%9E%BC%E1%9E%98%E1%9E%B7%E1%9E%86%E1%9F%92%E1%9E%93%E1%9E%BE%E1%9E%98%20FT.jpg","upload_status":false},"label":"Movies, Thai - Khmer, Series Movies,Series Thai,  Continue, Thai Continue, withads","list":[{"vid":"4199026788956","part":1,"vtype":"ok"},{"vid":"4201226046044","part":2,"vtype":"ok"},{"vid":"4203361471068","part":3,"vtype":"ok"},{"vid":"4210735123036","part":4,"vtype":"ok"},{"vid":"4228973595228","part":5,"vtype":"ok"},{"vid":"4230886853212","part":6,"vtype":"ok"},{"vid":"4239299054172","part":7,"vtype":"ok"},{"vid":"4244761021020","part":8,"vtype":"ok"},{"vid":"4252988541532","part":9,"vtype":"ok"},{"vid":"4271412808284","part":10,"vtype":"ok"},{"vid":"4273691560540","part":11,"vtype":"ok"},{"vid":"4280091478620","part":12,"vtype":"ok"},{"vid":"4285352839772","part":13,"vtype":"ok"},{"vid":"4291373566556","part":14,"vtype":"ok"},{"vid":"4301001984604","part":15,"vtype":"ok"},{"vid":"4314065341020","part":16,"vtype":"ok"},{"vid":"4314065275484","part":17,"vtype":"ok"},{"vid":"4316579891804","part":18,"vtype":"ok"},{"vid":"4323659352668","part":19,"vtype":"ok"},{"vid":"4349799238236","part":20,"vtype":"ok"},{"vid":"4355743353436","part":21,"vtype":"ok"},{"vid":"4362541861468","part":22,"vtype":"ok"},{"vid":"4370946001500","part":23,"vtype":"ok"},{"vid":"4388435069532","part":24,"vtype":"ok"},{"vid":"4394010085980","part":25,"vtype":"ok"},{"vid":"4396649941596","part":26,"vtype":"ok"},{"vid":"4399466416732","part":27,"vtype":"ok"},{"vid":"4402162698844","part":28,"vtype":"ok"},{"vid":"4418463795804","part":29,"vtype":"ok"},{"vid":"4423995361884","part":30,"vtype":"ok"},{"vid":"4432425519708","part":31,"vtype":"ok"},{"vid":"4432417131100","part":32,"vtype":"ok"},{"vid":"4436588628572","part":33,"vtype":"ok"},{"vid":"4439425026652","part":34,"vtype":"ok"},{"vid":"4448043534940","part":35,"vtype":"ok"},{"vid":"4451466152540","part":36,"vtype":"ok"},{"vid":"4455478135388","part":37,"vtype":"ok"},{"vid":"4458252536412","part":38,"vtype":"ok"},{"vid":"4467748768348","part":39,"vtype":"ok"},{"vid":"4478870948444","part":40,"vtype":"ok"},{"vid":"4483484027484","part":41,"vtype":"ok"},{"vid":"4487078742620","part":42,"vtype":"ok"},{"vid":"4491571104348","part":43,"vtype":"ok"},{"vid":"4498400873052","part":44,"vtype":"ok"},{"vid":"4505744050780","part":45,"vtype":"ok"},{"vid":"4511163681372","part":46,"vtype":"ok"},{"vid":"4518518590044","part":47,"vtype":"ok"},{"vid":"4523451484764","part":48,"vtype":"ok"},{"vid":"4531589483100","part":49,"vtype":"ok"},{"vid":"4539925858908","part":50,"vtype":"ok"},{"vid":"4543698307676","part":51,"vtype":"ok"},{"vid":"4548685400668","part":52,"vtype":"ok"},{"vid":"4565872675420","part":53,"vtype":"ok"},{"vid":"4565872806492","part":54,"vtype":"ok"}],"file_name":"thai-mea-khom-chhnas-pas-mea-phum-chhnerm.json","link":"https:\/\/www.fantafilm.us\/2022\/10\/mea-khom-chhnas-pas-mea-phum-chhnerm.html"}