{"title":"Sno Donghem Sne id 871ac9ac5 || part [ 34 ]","type":"vdolist","object_id":"107019511557162660876","pid":"871ac9ac5","image":{"url":"https:\/\/blogger.googleusercontent.com\/img\/b\/R29vZ2xl\/AVvXsEgRl6JrVUKbU9l18KPvdipOzDrpyw30dNbu_gsyFXMFM529UqKW1Tj4yRD_nZxYx5OK9ueVLd_KXiKOAVZdJ8RenQf7fhPp92QamvQR98nadoAUoHvxtyXlpVV-L0JnHXsr7bCvJRaBTl_VxStQK5bs0Q5Wx1yd1l25WVhaPbzYjot2d3bgtGRmZ0hl\/w0\/4.jpg","upload_status":false},"label":"Movies, Thai - Khmer, Series Movies, Series Thai, withads","list":[{"vid":"4928421890652","part":1,"vtype":"ok"},{"vid":"4935787285084","part":2,"vtype":"ok"},{"vid":"4939014277724","part":3,"vtype":"ok"},{"vid":"4945328474716","part":4,"vtype":"ok"},{"vid":"4945328409180","part":5,"vtype":"ok"},{"vid":"4961693010524","part":6,"vtype":"ok"},{"vid":"4981057981020","part":7,"vtype":"ok"},{"vid":"4988806171228","part":8,"vtype":"ok"},{"vid":"4997143530076","part":9,"vtype":"ok"},{"vid":"5006100925020","part":10,"vtype":"ok"},{"vid":"5023552637532","part":11,"vtype":"ok"},{"vid":"5040660351580","part":12,"vtype":"ok"},{"vid":"5059191704156","part":13,"vtype":"ok"},{"vid":"5059191638620","part":14,"vtype":"ok"},{"vid":"5065183726172","part":15,"vtype":"ok"},{"vid":"5075884182108","part":16,"vtype":"ok"},{"vid":"5149138029148","part":17,"vtype":"ok"},{"vid":"5149137963612","part":18,"vtype":"ok"},{"vid":"5155022703196","part":19,"vtype":"ok"},{"vid":"5155022637660","part":20,"vtype":"ok"},{"vid":"5183628053084","part":21,"vtype":"ok"},{"vid":"5194588818012","part":22,"vtype":"ok"},{"vid":"5194588686940","part":23,"vtype":"ok"},{"vid":"5220474227292","part":24,"vtype":"ok"},{"vid":"5220474161756","part":25,"vtype":"ok"},{"vid":"5229892864604","part":26,"vtype":"ok"},{"vid":"5249206913628","part":27,"vtype":"ok"},{"vid":"5249206979164","part":28,"vtype":"ok"},{"vid":"5261844810332","part":29,"vtype":"ok"},{"vid":"5275399162460","part":30,"vtype":"ok"},{"vid":"5284845652572","part":31,"vtype":"ok"},{"vid":"5291352066652","part":32,"vtype":"ok"},{"vid":"5304461363804","part":33,"vtype":"ok"},{"vid":"5313205504604","part":34,"vtype":"ok"}],"file_name":"thai-sno-donghem-sne.json","link":"https:\/\/www.fantafilm.us\/2023\/03\/sno-donghem-sne.html","bid":"871ac9ac5"}