{"title":"[01-28 EP] Vireak Chon Moha thang id fb623997a || part [ 28 ]","type":"vdolist","object_id":"104724801112461222967","pid":"fb623997a","image":{"url":"https:\/\/blogger.googleusercontent.com\/img\/b\/R29vZ2xl\/AVvXsEhkuMxclAR73D0gJMUCqzCXPLmMhixFBxVof_bjQVqVbMzzUYjTVoge7PrltKWvSKbEvcxkHs6AQPv3baMTn5HBwi7rfc4IENxjYJScetZQUqIywSm1U2iADQScovrtQtoLC-ndbI1tbSAY2xsT9-X9AKKDFSi1BN6vyoEE_i2ONZfhk_mAlMjglh1_Jw\/w0\/2.jpg","upload_status":false},"label":"Movies, chinese movies, Series Movie, Chinese Continue, withads","list":[{"vid":"https:\/\/bigf.bigo.sg\/asia_live\/V4s7\/1AgxtM.mp4","part":1,"vtype":"iframe"},{"vid":"https:\/\/bigf.bigo.sg\/asia_live\/V4s7\/02Y1Sm.mp4","part":2,"vtype":"iframe"},{"vid":"https:\/\/bigf.bigo.sg\/asia_live\/V4s7\/06c2lW.mp4","part":3,"vtype":"iframe"},{"vid":"https:\/\/bigf.bigo.sg\/asia_live\/V4s7\/03Z1D7.mp4","part":4,"vtype":"iframe"},{"vid":"https:\/\/bigf.bigo.sg\/asia_live\/V4s7\/0vZOlU.mp4","part":5,"vtype":"iframe"},{"vid":"https:\/\/bigf.bigo.sg\/asia_live\/V4s7\/2MAU4G.mp4","part":6,"vtype":"iframe"},{"vid":"https:\/\/bigf.bigo.sg\/asia_live\/V4s7\/0CZOwp.mp4","part":7,"vtype":"iframe"},{"vid":"https:\/\/bigf.bigo.sg\/asia_live\/V4s7\/07ULHu.mp4","part":8,"vtype":"iframe"},{"vid":"https:\/\/bigf.bigo.sg\/asia_live\/V4s7\/2CZfAR.mp4","part":9,"vtype":"iframe"},{"vid":"https:\/\/bigf.bigo.sg\/asia_live\/V4s7\/1CZJ53.mp4","part":10,"vtype":"iframe"},{"vid":"https:\/\/bigf.bigo.sg\/asia_live\/V4s7\/2BbBaY.mp4","part":11,"vtype":"iframe"},{"vid":"https:\/\/bigf.bigo.sg\/asia_live\/V4s7\/17gDqW.mp4","part":12,"vtype":"iframe"},{"vid":"https:\/\/bigf.bigo.sg\/asia_live\/V4s7\/14kDnV.mp4","part":13,"vtype":"iframe"},{"vid":"https:\/\/bigf.bigo.sg\/asia_live\/V4s7\/0NCFxq.mp4","part":14,"vtype":"iframe"},{"vid":"https:\/\/bigf.bigo.sg\/asia_live\/V4s7\/0wtSPI.mp4","part":15,"vtype":"iframe"},{"vid":"https:\/\/bigf.bigo.sg\/asia_live\/V4s7\/0JNTBB.mp4","part":16,"vtype":"iframe"},{"vid":"https:\/\/bigf.bigo.sg\/asia_live\/V4s7\/2CMnIM.mp4","part":17,"vtype":"iframe"},{"vid":"https:\/\/bigf.bigo.sg\/asia_live\/V4s7\/24NL9a.mp4","part":18,"vtype":"iframe"},{"vid":"https:\/\/bigf.bigo.sg\/asia_live\/V4s7\/25YNGV.mp4","part":19,"vtype":"iframe"},{"vid":"https:\/\/bigf.bigo.sg\/asia_live\/V4s7\/2Cm2pY.mp4","part":20,"vtype":"iframe"},{"vid":"https:\/\/bigf.bigo.sg\/asia_live\/V4s7\/24oo4m.mp4","part":21,"vtype":"iframe"},{"vid":"https:\/\/bigf.bigo.sg\/asia_live\/V4s7\/0C5PsY.mp4","part":22,"vtype":"iframe"},{"vid":"https:\/\/bigf.bigo.sg\/asia_live\/V4s7\/256iiy.mp4","part":23,"vtype":"iframe"},{"vid":"https:\/\/bigf.bigo.sg\/asia_live\/V4s7\/25G9EO.mp4","part":24,"vtype":"iframe"},{"vid":"https:\/\/bigf.bigo.sg\/asia_live\/V4s7\/2DYFNA.mp4","part":25,"vtype":"iframe"},{"vid":"https:\/\/bigf.bigo.sg\/asia_live\/V4s7\/0PuCkG.mp4","part":26,"vtype":"iframe"},{"vid":"https:\/\/bigf.bigo.sg\/asia_live\/V4s7\/25kQO0.mp4","part":27,"vtype":"iframe"},{"vid":"https:\/\/bigf.bigo.sg\/asia_live\/V4s7\/0VHV3j.mp4","part":28,"vtype":"iframe"}],"file_name":"china-01-28-ep-vireak-chon-moha-thang.json","link":"https:\/\/www.sundaydrama.com\/2023\/06\/vireak-chon-moha-thang.html","bid":"fb623997a"}