{"title":"Chom Norng Sneah Krou Chab Beysach id 8e3694f46 || part [ 1 ]","type":"vdolist","object_id":"104724801112461222967","pid":"8e3694f46","image":{"url":"https:\/\/www.video4khmer37.com\/images\/subcat\/2673\/11325.jpg","upload_status":false},"label":"Movies, chinese movies, Series Movie, Chinese Continue, withads","list":[{"vid":"4584146930315","part":1,"vtype":"ok"}],"file_name":"china-chom-norng-sneah-krou-chab-beysach.json","link":"https:\/\/www.video4khmer37.com\/title\/khmer-chinese-drama-chom-norng-sneah-krou-chab-beysach-album-11325-page-1.html","bid":"8e3694f46"}